webm.py
webm-0.12.1.dist-info/LICENSE.txt
webm-0.12.1.dist-info/METADATA
webm-0.12.1.dist-info/RECORD
webm-0.12.1.dist-info/WHEEL
webm-0.12.1.dist-info/entry_points.txt
webm-0.12.1.dist-info/top_level.txt
